mhdtools/__init__.py
mhdtools/common.py
mhdtools/mhdview.py
mhdtools/.pkginfo/version
mhdtools-1.0.1.dist-info/licenses/LICENSE
mhdtools-1.0.1.dist-info/METADATA
mhdtools-1.0.1.dist-info/WHEEL
mhdtools-1.0.1.dist-info/entry_points.txt
mhdtools-1.0.1.dist-info/top_level.txt
mhdtools-1.0.1.dist-info/RECORD
