Metadata-Version: 2.4
Name: mhdtools
Version: 1.0.1
Summary: Tools to manipulate MHD/RAW files
Home-page: https://github.com/alexis-pereda/mhdtools
Author: Alexis Pereda
Author-email: alexis@pereda.fr
License-Expression: MIT
Project-URL: Homepage, https://github.com/alexis-pereda/mhdtools
Project-URL: Issues, https://github.com/alexis-pereda/mhdtools/issues
Classifier: Programming Language :: Python :: 3
Classifier: Operating System :: OS Independent
Requires-Python: >=3.8
License-File: LICENSE
Requires-Dist: click
Requires-Dist: matplotlib
Requires-Dist: numpy
Requires-Dist: scipy
Requires-Dist: SimpleITK
Dynamic: author-email
Dynamic: home-page
Dynamic: license-file
Dynamic: requires-dist
